{
  "mapFile": "Map/map3.tmx",
  "playerStartPosition": {
    "x": 3,
    "y": 15
  },
  "enemySpawnPoints": [
    { "x": 12, "y": 11.8 },
    { "x": 11.4, "y": 11.8 },
    { "x": 18.5, "y": 12.8 },
    { "x": 21.8, "y": 12.3 },
    { "x": 22.8, "y": 12.3 },
    { "x": 23.8, "y": 12.3 },
    { "x": 31, "y": 9.8 },
    { "x": 33.5, "y": 9.8 },
    { "x": 35, "y":  16.8},
    { "x": 42, "y":  17.3},
    { "x": 47.5, "y":  16.8},
    { "x": 55, "y":  18.8},
    { "x": 57.5, "y":  18.8}
  ],
  "levelCompletionPosition": {
    "x": 60.9,
    "y": 18.8
  }
}
